cdk_appsync_transformer/__init__.py
cdk_appsync_transformer/py.typed
cdk_appsync_transformer/_jsii/__init__.py
cdk_appsync_transformer/_jsii/cdk-appsync-transformer@1.138.3.jsii.tgz
cdk_appsync_transformer-1.138.3.dist-info/LICENSE
cdk_appsync_transformer-1.138.3.dist-info/METADATA
cdk_appsync_transformer-1.138.3.dist-info/WHEEL
cdk_appsync_transformer-1.138.3.dist-info/top_level.txt
cdk_appsync_transformer-1.138.3.dist-info/RECORD
