Metadata-Version: 2.1
Name: cdk-appsync-transformer
Version: 1.138.3
Summary: cdk-appsync-transformer
Home-page: https://github.com/kcwinner/cdk-appsync-transformer.git
Author: Ken Winner<kcswinner@gmail.com>
License: Apache-2.0
Project-URL: Source, https://github.com/kcwinner/cdk-appsync-transformer.git
Platform: UNKNOWN
Classifier: Intended Audience :: Developers
Classifier: Operating System :: OS Independent
Classifier: Programming Language :: JavaScript
Classifier: Programming Language :: Python :: 3 :: Only
Classifier: Programming Language :: Python :: 3.6
Classifier: Programming Language :: Python :: 3.7
Classifier: Programming Language :: Python :: 3.8
Classifier: Programming Language :: Python :: 3.9
Classifier: Typing :: Typed
Classifier: Development Status :: 4 - Beta
Classifier: License :: OSI Approved
Requires-Python: >=3.6
License-File: LICENSE
Requires-Dist: aws-cdk.aws-appsync (<2.0.0,>=1.138.0)
Requires-Dist: aws-cdk.aws-cognito (<2.0.0,>=1.138.0)
Requires-Dist: aws-cdk.aws-dynamodb (<2.0.0,>=1.138.0)
Requires-Dist: aws-cdk.aws-iam (<2.0.0,>=1.138.0)
Requires-Dist: aws-cdk.aws-lambda (<2.0.0,>=1.138.0)
Requires-Dist: aws-cdk.core (<2.0.0,>=1.138.0)
Requires-Dist: constructs (<4.0.0,>=3.2.27)
Requires-Dist: jsii (<2.0.0,>=1.34.0)
Requires-Dist: publication (>=0.0.3)
